stape/__init__.py
stape/version.py
stacore-0.1.dist-info/LICENSE.txt
stacore-0.1.dist-info/METADATA
stacore-0.1.dist-info/WHEEL
stacore-0.1.dist-info/top_level.txt
stacore-0.1.dist-info/RECORD
